README.rst
setup.py
jw/__init__.py
jw.grbackup.egg-info/PKG-INFO
jw.grbackup.egg-info/SOURCES.txt
jw.grbackup.egg-info/dependency_links.txt
jw.grbackup.egg-info/entry_points.txt
jw.grbackup.egg-info/namespace_packages.txt
jw.grbackup.egg-info/requires.txt
jw.grbackup.egg-info/top_level.txt
jw/grbackup/__init__.py
jw/grbackup/main.py