Metadata-Version: 1.1
Name: jw.grbackup
Version: 0.2
Summary: Gentoo rsync backup -- a simple differential backup script for Gentoo Linux
Home-page: https://pypi.python.org/pypi/jw.grbackup
Author: Johnny Wezel
Author-email: dev-jay@wezel.name
License: GPL
Keywords: backup,utility
Platform: POSIX
Classifier: Development Status :: 5 - Production/Stable
Classifier: Environment :: Console
Classifier: Intended Audience :: System Administrators
Classifier: License :: OSI Approved :: GNU General Public License v3 or later (GPLv3+)
Classifier: Natural Language :: English
Classifier: Operating System :: POSIX
Classifier: Programming Language :: Python :: 2.7
Classifier: Topic :: System :: Archiving :: Backup
Classifier: Topic :: System :: Archiving :: Mirroring
Classifier: Topic :: Utilities
